{"nodes": [{"id": "ui_toggle_toggle", "name": "Toggle", "type": "component", "file_type": "code", "confidence_score": 1.0, "source_file": "ui/src/components/ui/toggle.tsx", "summary": "Toggle button component wrapping BaseToggle from @base-ui/react with styling variants (default/outline) and sizes (default/sm/lg)"}, {"id": "ui_toggle_variants", "name": "toggleVariants", "type": "style_config", "file_type": "code", "confidence_score": 1.0, "source_file": "ui/src/components/ui/toggle.tsx", "summary": "CVA (class-variance-authority) variant definitions for Toggle component"}, {"id": "ui_toggle_file", "name": "toggle.tsx", "type": "file", "file_type": "code", "confidence_score": 1.0, "source_file": "ui/src/components/ui/toggle.tsx", "summary": "Toggle UI component with variants and sizes"}], "edges": [], "hyperedges": []}