{"nodes": [{"id": "public_sitewebmanifest_openchamber", "name": "OpenChamber", "type": "entity", "file_type": "document", "confidence_score": 1.0, "source_file": "web/public/site.webmanifest"}, {"id": "public_sitewebmanifest_opencode", "name": "OpenCode", "type": "entity", "file_type": "document", "confidence_score": 1.0, "source_file": "web/public/site.webmanifest"}, {"id": "public_sitewebmanifest_pwa", "name": "PWA (Progressive Web App)", "type": "concept", "file_type": "document", "confidence_score": 1.0, "source_file": "web/public/site.webmanifest"}, {"id": "public_sitewebmanifest_ai-coding-companion", "name": "AI Coding Companion", "type": "concept", "file_type": "document", "confidence_score": 1.0, "source_file": "web/public/site.webmanifest"}], "edges": [], "hyperedges": []}