{"nodes": [{"id": "ui_package_name", "label": "@openchamber/ui package", "type": "entity", "file_type": "code", "confidence_score": 1.0, "source_file": "ui/package.json", "properties": {"name": "@openchamber/ui", "version": "1.13.3", "private": true, "type": "module", "entry": "src/main.tsx"}}, {"id": "ui_package_scripts", "label": "Package npm scripts", "type": "entity", "file_type": "code", "confidence_score": 1.0, "source_file": "ui/package.json", "properties": {"dev": "tsc --noEmit --watch", "build": "tsc --noEmit", "type_check": "tsc --noEmit", "lint": "eslint ./src/**/*.{ts,tsx} --config ../../eslint.config.js"}}, {"id": "ui_package_react", "label": "React 19.1", "type": "entity", "file_type": "code", "confidence_score": 1.0, "source_file": "ui/package.json", "properties": {"package": "react", "version": "^19.1.1", "scope": "dependency"}}, {"id": "ui_package_reactdom", "label": "React DOM 19.1", "type": "entity", "file_type": "code", "confidence_score": 1.0, "source_file": "ui/package.json", "properties": {"package": "react-dom", "version": "^19.1.1", "scope": "dependency"}}, {"id": "ui_package_codemirror", "label": "CodeMirror packages", "type": "entity", "file_type": "code", "confidence_score": 1.0, "source_file": "ui/package.json", "properties": {"packages": ["@codemirror/autocomplete", "@codemirror/commands", "@codemirror/lang-cpp", "@codemirror/lang-css", "@codemirror/lang-go", "@codemirror/lang-html", "@codemirror/lang-javascript", "@codemirror/lang-json", "@codemirror/lang-markdown", "@codemirror/lang-python", "@codemirror/lang-rust", "@codemirror/lang-sql", "@codemirror/lang-xml", "@codemirror/lang-yaml", "@codemirror/language", "@codemirror/language-data", "@codemirror/legacy-modes", "@codemirror/lint", "@codemirror/search", "@codemirror/state", "@codemirror/view"], "scope": "dependency", "purpose": "code-editor"}}, {"id": "ui_package_dndkit", "label": "dnd-kit packages", "type": "entity", "file_type": "code", "confidence_score": 1.0, "source_file": "ui/package.json", "properties": {"packages": ["@dnd-kit/core", "@dnd-kit/sortable", "@dnd-kit/utilities"], "scope": "dependency", "purpose": "drag-and-drop"}}, {"id": "ui_package_opencode_sdk", "label": "@opencode-ai/sdk", "type": "entity", "file_type": "code", "confidence_score": 1.0, "source_file": "ui/package.json", "properties": {"package": "@opencode-ai/sdk", "version": "^1.17.9", "scope": "dependency"}}, {"id": "ui_package_zustand", "label": "Zustand state management", "type": "entity", "file_type": "code", "confidence_score": 1.0, "source_file": "ui/package.json", "properties": {"package": "zustand", "version": "^5.0.8", "scope": "dependency"}}, {"id": "ui_package_tailwind_deps", "label": "Tailwind CSS dependencies", "type": "entity", "file_type": "code", "confidence_score": 1.0, "source_file": "ui/package.json", "properties": {"packages": ["clsx", "tailwind-merge", "class-variance-authority", "tailwindcss"], "scopes": ["dependency", "devDependency"]}}, {"id": "ui_package_typescript", "label": "TypeScript 5.9", "type": "entity", "file_type": "code", "confidence_score": 1.0, "source_file": "ui/package.json", "properties": {"package": "typescript", "version": "~5.9.0", "scope": "devDependency"}}, {"id": "ui_package_vite", "label": "Vite 7.1", "type": "entity", "file_type": "code", "confidence_score": 1.0, "source_file": "ui/package.json", "properties": {"package": "vite", "version": "^7.1.2", "scope": "devDependency"}}, {"id": "ui_package_eslint", "label": "ESLint 9.33", "type": "entity", "file_type": "code", "confidence_score": 1.0, "source_file": "ui/package.json", "properties": {"package": "eslint", "version": "^9.33.0", "scope": "devDependency"}}, {"id": "ui_package_replit_codemirror_vim", "label": "@replit/codemirror-vim", "type": "entity", "file_type": "code", "confidence_score": 1.0, "source_file": "ui/package.json", "properties": {"package": "@replit/codemirror-vim", "version": "^6.3.0", "scope": "dependency", "purpose": "vim-keybindings"}}, {"id": "ui_package_shiki", "label": "Shiki syntax highlighter", "type": "entity", "file_type": "code", "confidence_score": 1.0, "source_file": "ui/package.json", "properties": {"package": "shiki", "version": "^3.23.0", "scope": "dependency", "purpose": "syntax-highlighting"}}, {"id": "ui_shared_baseui_react", "name": "@base-ui/react", "type": "library", "file_type": "code", "source_file": "ui/package.json", "confidence_score": 0.95, "extraction": "INFERRED", "attributes": {"components": ["Checkbox", "Collapsible", "ContextMenu", "Dialog", "Menu"]}}, {"id": "ui_shared_cmdk", "name": "cmdk", "type": "library", "file_type": "code", "source_file": "ui/package.json", "confidence_score": 0.95, "extraction": "INFERRED", "attributes": {"component": "Command"}}], "edges": [], "hyperedges": [{"id": "ui_runtime_dependency_group", "label": "Core runtime dependencies", "nodes": ["ui_package_react", "ui_package_reactdom", "ui_package_codemirror", "ui_package_dndkit", "ui_package_opencode_sdk", "ui_package_zustand"], "confidence_score": 0.85, "source_file": "ui/package.json", "properties": {"relationship": "shared_runtime_dependency", "description": "Primary runtime dependencies of @openchamber/ui"}}, {"id": "ui_toolchain_group", "label": "Build and lint toolchain", "nodes": ["ui_package_typescript", "ui_package_vite", "ui_package_eslint"], "confidence_score": 0.85, "source_file": "ui/package.json", "properties": {"relationship": "dev_toolchain", "description": "Development toolchain for type-checking, bundling, and linting"}}]}